{"createdAt":1474220000,"ttl":1800,"data":"{\"36424884\":[{\"name\":\"Garen's Crusaders\",\"tier\":\"PLATINUM\",\"queue\":\"RANKED_SOLO_5x5\",\"entries\":[{\"playerOrTeamId\":\"36424884\",\"playerOrTeamName\":\"p\u00e2nkiller\",\"division\":\"II\",\"leaguePoints\":27,\"wins\":271,\"losses\":277,\"playstyle\":\"SQUAD\",\"isHotStreak\":false,\"isVeteran\":true,\"isFreshBlood\":false,\"isInactive\":false}]},{\"name\":\"Blitzcrank's Swashbucklers\",\"tier\":\"SILVER\",\"queue\":\"RANKED_TEAM_3x3\",\"entries\":[{\"playerOrTeamId\":\"TEAM-a7844ef0-c502-11e4-8e2b-782bcb46f3e4\",\"playerOrTeamName\":\"GreatBaitMateIRateEight\",\"division\":\"II\",\"leaguePoints\":82,\"wins\":12,\"losses\":7,\"playstyle\":\"NONE\",\"isHotStreak\":false,\"isVeteran\":false,\"isFreshBlood\":false,\"isInactive\":false}]}],\"33794680\":[{\"name\":\"Janna's Paladins\",\"tier\":\"GOLD\",\"queue\":\"RANKED_SOLO_5x5\",\"entries\":[{\"playerOrTeamId\":\"33794680\",\"playerOrTeamName\":\"EBERHARDTX\",\"division\":\"II\",\"leaguePoints\":48,\"wins\":110,\"losses\":107,\"playstyle\":\"NONE\",\"isHotStreak\":false,\"isVeteran\":true,\"isFreshBlood\":false,\"isInactive\":false}]},{\"name\":\"Blitzcrank's Swashbucklers\",\"tier\":\"SILVER\",\"queue\":\"RANKED_TEAM_3x3\",\"entries\":[{\"playerOrTeamId\":\"TEAM-a7844ef0-c502-11e4-8e2b-782bcb46f3e4\",\"playerOrTeamName\":\"GreatBaitMateIRateEight\",\"division\":\"II\",\"leaguePoints\":82,\"wins\":12,\"losses\":7,\"playstyle\":\"NONE\",\"isHotStreak\":false,\"isVeteran\":false,\"isFreshBlood\":false,\"isInactive\":false}]}],\"28219720\":[{\"name\":\"Urgot's Berserkers\",\"tier\":\"PLATINUM\",\"queue\":\"RANKED_SOLO_5x5\",\"entries\":[{\"playerOrTeamId\":\"28219720\",\"playerOrTeamName\":\"YoGurtCZ\",\"division\":\"IV\",\"leaguePoints\":19,\"wins\":82,\"losses\":97,\"playstyle\":\"NONE\",\"isHotStreak\":false,\"isVeteran\":true,\"isFreshBlood\":false,\"isInactive\":false}]},{\"name\":\"Pantheon's Exemplars\",\"tier\":\"SILVER\",\"queue\":\"RANKED_TEAM_3x3\",\"entries\":[{\"playerOrTeamId\":\"TEAM-7c28eca0-4df2-11e6-96ba-782bcb46f3e4\",\"playerOrTeamName\":\"Blaze Universe\",\"division\":\"V\",\"leaguePoints\":61,\"wins\":7,\"losses\":7,\"playstyle\":\"NONE\",\"isHotStreak\":false,\"isVeteran\":false,\"isFreshBlood\":false,\"isInactive\":false}]}],\"44016035\":[{\"name\":\"Galio's Warriors\",\"tier\":\"PLATINUM\",\"queue\":\"RANKED_SOLO_5x5\",\"entries\":[{\"playerOrTeamId\":\"44016035\",\"playerOrTeamName\":\"fapallday\",\"division\":\"I\",\"leaguePoints\":0,\"wins\":145,\"losses\":146,\"playstyle\":\"SQUAD\",\"isHotStreak\":false,\"isVeteran\":true,\"isFreshBlood\":false,\"isInactive\":false}]}],\"31573623\":[{\"name\":\"Corki's Buddies\",\"tier\":\"PLATINUM\",\"queue\":\"RANKED_SOLO_5x5\",\"entries\":[{\"playerOrTeamId\":\"31573623\",\"playerOrTeamName\":\"Strygwyr is op\",\"division\":\"III\",\"leaguePoints\":75,\"wins\":184,\"losses\":172,\"playstyle\":\"SOLO\",\"isHotStreak\":false,\"isVeteran\":true,\"isFreshBlood\":false,\"isInactive\":false}]}],\"40747806\":[{\"name\":\"Ziggs's Paragons\",\"tier\":\"PLATINUM\",\"queue\":\"RANKED_SOLO_5x5\",\"entries\":[{\"playerOrTeamId\":\"40747806\",\"playerOrTeamName\":\"Just A Gent\",\"division\":\"III\",\"leaguePoints\":70,\"wins\":177,\"losses\":179,\"playstyle\":\"SQUAD\",\"isHotStreak\":true,\"isVeteran\":true,\"isFreshBlood\":false,\"isInactive\":false}]}],\"224445\":[{\"name\":\"Rengar's Captains\",\"tier\":\"PLATINUM\",\"queue\":\"RANKED_SOLO_5x5\",\"entries\":[{\"playerOrTeamId\":\"224445\",\"playerOrTeamName\":\"Szatan\",\"division\":\"V\",\"leaguePoints\":57,\"wins\":132,\"losses\":133,\"playstyle\":\"SQUAD\",\"isHotStreak\":false,\"isVeteran\":true,\"isFreshBlood\":false,\"isInactive\":false}]}],\"36334117\":[{\"name\":\"Twitch's Gladiators\",\"tier\":\"PLATINUM\",\"queue\":\"RANKED_SOLO_5x5\",\"entries\":[{\"playerOrTeamId\":\"36334117\",\"playerOrTeamName\":\"NowySezonNowyJa\",\"division\":\"IV\",\"leaguePoints\":20,\"wins\":232,\"losses\":226,\"playstyle\":\"SQUAD\",\"isHotStreak\":false,\"isVeteran\":false,\"isFreshBlood\":false,\"isInactive\":false}]},{\"name\":\"Sion's Outlaws\",\"tier\":\"BRONZE\",\"queue\":\"RANKED_TEAM_5x5\",\"entries\":[{\"playerOrTeamId\":\"TEAM-89895800-63b8-11e5-853a-782bcb46f3e4\",\"playerOrTeamName\":\"PryncyPoke\",\"division\":\"V\",\"leaguePoints\":0,\"wins\":1,\"losses\":4,\"playstyle\":\"NONE\",\"isHotStreak\":false,\"isVeteran\":false,\"isFreshBlood\":false,\"isInactive\":false}]}],\"26110538\":[{\"name\":\"Udyr's Berserkers\",\"tier\":\"PLATINUM\",\"queue\":\"RANKED_SOLO_5x5\",\"entries\":[{\"playerOrTeamId\":\"26110538\",\"playerOrTeamName\":\"Gruj\u00e2\",\"division\":\"IV\",\"leaguePoints\":99,\"wins\":171,\"losses\":159,\"playstyle\":\"SQUAD\",\"isHotStreak\":false,\"isVeteran\":true,\"isFreshBlood\":false,\"isInactive\":false}]},{\"name\":\"Gangplank's Mercenaries\",\"tier\":\"BRONZE\",\"queue\":\"RANKED_TEAM_5x5\",\"entries\":[{\"playerOrTeamId\":\"TEAM-5dcad3e0-6554-11e5-b14b-782bcb4d190f\",\"playerOrTeamName\":\"StrujaDifuzije\",\"division\":\"IV\",\"leaguePoints\":0,\"wins\":2,\"losses\":3,\"playstyle\":\"NONE\",\"isHotStreak\":false,\"isVeteran\":false,\"isFreshBlood\":false,\"isInactive\":false}]},{\"name\":\"Anivia's Spellswords\",\"tier\":\"SILVER\",\"queue\":\"RANKED_TEAM_5x5\",\"entries\":[{\"playerOrTeamId\":\"TEAM-836648f0-68a5-11e6-85bc-782bcb4d190f\",\"playerOrTeamName\":\"Nece da mi pulaju\",\"division\":\"IV\",\"leaguePoints\":0,\"wins\":5,\"losses\":0,\"playstyle\":\"NONE\",\"isHotStreak\":false,\"isVeteran\":false,\"isFreshBlood\":false,\"isInactive\":false}]}]}"}