{"createdAt":1474237239,"ttl":3600,"data":"{\"summonerId\":1713609,\"playerStatSummaries\":[{\"playerStatSummaryType\":\"AramUnranked5x5\",\"wins\":1,\"modifyDate\":1461669801000,\"aggregatedStats\":{\"totalChampionKills\":21,\"totalTurretsKilled\":1,\"totalAssists\":23}},{\"playerStatSummaryType\":\"CoopVsAI\",\"wins\":3,\"modifyDate\":1461669801000,\"aggregatedStats\":{\"totalChampionKills\":41,\"totalMinionKills\":240,\"totalTurretsKilled\":1,\"totalNeutralMinionsKilled\":23,\"totalAssists\":19}},{\"playerStatSummaryType\":\"Unranked\",\"wins\":18,\"modifyDate\":1461669801000,\"aggregatedStats\":{\"totalChampionKills\":278,\"totalMinionKills\":2765,\"totalTurretsKilled\":26,\"totalNeutralMinionsKilled\":295,\"totalAssists\":204}},{\"playerStatSummaryType\":\"Unranked3x3\",\"wins\":0,\"modifyDate\":1461669801000,\"aggregatedStats\":{}}]}"}